casex/__init__.py
casex/aircraft_specs.py
casex/annex_f_parms.py
casex/annex_f_tables.py
casex/ballistic_descent_models.py
casex/constants.py
casex/conversion.py
casex/critical_area_models.py
casex/enums.py
casex/exceptions.py
casex/explosion_models.py
casex/figures.py
casex/flyaway_models.py
casex/friction_coefficient.py
casex/ground_risk_buffer.py
casex/misc.py
casex/obstacle_simulation.py
casex/obstacles.py
casex/temporary_testing_figures.py
casex-1.2.3.dist-info/LICENSE.txt
casex-1.2.3.dist-info/METADATA
casex-1.2.3.dist-info/WHEEL
casex-1.2.3.dist-info/top_level.txt
casex-1.2.3.dist-info/RECORD
