Metadata-Version: 2.1
Name: casex
Version: 1.2.3
Summary: Casualty expectation toolbox
Home-page: UNKNOWN
Author: Anders la Cour-Harbo et al
Author-email: anders@lacourfamily.dk
License: CC-BY-4.0
Platform: UNKNOWN
Classifier: Development Status :: 5 - Production/Stable
Classifier: License :: Other/Proprietary License
Classifier: Programming Language :: Python :: 3.7
Classifier: Topic :: Scientific/Engineering
Classifier: Intended Audience :: Science/Research
Classifier: Natural Language :: English
Requires-Python: >=3.6
License-File: LICENSE.txt
Requires-Dist: numpy
Requires-Dist: matplotlib
Requires-Dist: scipy
Requires-Dist: descartes
Requires-Dist: shapely
